LICENSE
MANIFEST.in
setup.py
django_pastebin.egg-info/PKG-INFO
django_pastebin.egg-info/SOURCES.txt
django_pastebin.egg-info/dependency_links.txt
django_pastebin.egg-info/not-zip-safe
django_pastebin.egg-info/top_level.txt
example/__init__.py
example/urls.py
example/wsgi.py
example/pastebin/__init__.py
example/pastebin/forms.py
example/pastebin/models.py
example/pastebin/tests.py
example/pastebin/urls.py
example/pastebin/views.py
example/settings/__init__.py
example/settings/common.py
example/settings/heroku.py
example/settings/local.py
pastebin/__init__.py
pastebin/forms.py
pastebin/models.py
pastebin/tests.py
pastebin/urls.py
pastebin/views.py
pastebin/templates/djpaste/base.html
pastebin/templates/djpaste/create.html
pastebin/templates/djpaste/details.html
pastebin/templates/djpaste/help.html